[{"artists": {"href": "https://api.spotify.com/v1/search?query=artist%3AMICHELLE+CORDERO&type=artist&offset=0&limit=10", "items": [{"external_urls": {"spotify": "https://open.spotify.com/artist/6mwBayLYukgb8S1Af0fndm"}, "followers": {"href": null, "total": 230}, "genres": [], "href": "https://api.spotify.com/v1/artists/6mwBayLYukgb8S1Af0fndm", "id": "6mwBayLYukgb8S1Af0fndm", "images": [{"height": 640, "url": "https://i.scdn.co/image/9132830b4216242ab4abb0267715f05465a0753f", "width": 640}, {"height": 300, "url": "https://i.scdn.co/image/4859744c7f720b7e98297d4ccdfb0448ac09a2e8", "width": 300}, {"height": 64, "url": "https://i.scdn.co/image/958147606161b8cccbfc2926b3bf9c36162bf72e", "width": 64}], "name": "Michelle Cordero", "popularity": 24, "type": "artist", "uri": "spotify:artist:6mwBayLYukgb8S1Af0fndm"}], "limit": 10, "next": null, "offset": 0, "previous": null, "total": 1}}, {"spotify": "https://open.spotify.com/artist/6mwBayLYukgb8S1Af0fndm", "followers": 230, "id": "6mwBayLYukgb8S1Af0fndm", "images": [{"height": 640, "url": "https://i.scdn.co/image/9132830b4216242ab4abb0267715f05465a0753f", "width": 640}, {"height": 300, "url": "https://i.scdn.co/image/4859744c7f720b7e98297d4ccdfb0448ac09a2e8", "width": 300}, {"height": 64, "url": "https://i.scdn.co/image/958147606161b8cccbfc2926b3bf9c36162bf72e", "width": 64}], "name": "Michelle Cordero", "popularity": 24, "uri": "spotify:artist:6mwBayLYukgb8S1Af0fndm"}, {"artists": {"href": "https://api.spotify.com/v1/search?query=artist%3AMICAELLA+CATTANI&type=artist&offset=0&limit=10", "items": [{"external_urls": {"spotify": "https://open.spotify.com/artist/01kAgUWU808m0YEfr5DuHX"}, "followers": {"href": null, "total": 62}, "genres": [], "href": "https://api.spotify.com/v1/artists/01kAgUWU808m0YEfr5DuHX", "id": "01kAgUWU808m0YEfr5DuHX", "images": [{"height": 640, "url": "https://i.scdn.co/image/c37dcf7e315fad1f3c2dfb709bbbf78241816218", "width": 640}, {"height": 300, "url": "https://i.scdn.co/image/9d942486fc9c94c817f828979dc38634029d14de", "width": 300}, {"height": 64, "url": "https://i.scdn.co/image/5d2dc87a4f937605640e56d07f20c32bc0210d8f", "width": 64}], "name": "Micaella Cattani", "popularity": 1, "type": "artist", "uri": "spotify:artist:01kAgUWU808m0YEfr5DuHX"}], "limit": 10, "next": null, "offset": 0, "previous": null, "total": 1}}, {"spotify": "https://open.spotify.com/artist/01kAgUWU808m0YEfr5DuHX", "followers": 62, "id": "01kAgUWU808m0YEfr5DuHX", "images": [{"height": 640, "url": "https://i.scdn.co/image/c37dcf7e315fad1f3c2dfb709bbbf78241816218", "width": 640}, {"height": 300, "url": "https://i.scdn.co/image/9d942486fc9c94c817f828979dc38634029d14de", "width": 300}, {"height": 64, "url": "https://i.scdn.co/image/5d2dc87a4f937605640e56d07f20c32bc0210d8f", "width": 64}], "name": "Micaella Cattani", "popularity": 1, "uri": "spotify:artist:01kAgUWU808m0YEfr5DuHX"}, {"artists": {"href": "https://api.spotify.com/v1/search?query=artist%3AJORGE+LUIS+PERALTA&type=artist&offset=0&limit=10", "items": [{"external_urls": {"spotify": "https://open.spotify.com/artist/7aZfrK7IQ0t2vVCJOv5wDu"}, "followers": {"href": null, "total": 5}, "genres": [], "href": "https://api.spotify.com/v1/artists/7aZfrK7IQ0t2vVCJOv5wDu", "id": "7aZfrK7IQ0t2vVCJOv5wDu", "images": [{"height": 640, "url": "https://i.scdn.co/image/c324f1bce22fc4975b10c7a8bac91728e5d45217", "width": 640}, {"height": 320, "url": "https://i.scdn.co/image/37a6cf04c00c6fe9ab62a0a81e63a44ec30724c5", "width": 320}, {"height": 160, "url": "https://i.scdn.co/image/3aa17cab268c50638368e6336a52c89913a445d9", "width": 160}], "name": "Jorge Luis Peralta", "popularity": 0, "type": "artist", "uri": "spotify:artist:7aZfrK7IQ0t2vVCJOv5wDu"}], "limit": 10, "next": null, "offset": 0, "previous": null, "total": 1}}, {"spotify": "https://open.spotify.com/artist/7aZfrK7IQ0t2vVCJOv5wDu", "followers": 5, "id": "7aZfrK7IQ0t2vVCJOv5wDu", "images": [{"height": 640, "url": "https://i.scdn.co/image/c324f1bce22fc4975b10c7a8bac91728e5d45217", "width": 640}, {"height": 320, "url": "https://i.scdn.co/image/37a6cf04c00c6fe9ab62a0a81e63a44ec30724c5", "width": 320}, {"height": 160, "url": "https://i.scdn.co/image/3aa17cab268c50638368e6336a52c89913a445d9", "width": 160}], "name": "Jorge Luis Peralta", "popularity": 0, "uri": "spotify:artist:7aZfrK7IQ0t2vVCJOv5wDu"}, {"artists": {"href": "https://api.spotify.com/v1/search?query=artist%3AARMANDO+CHILIQUINGA&type=artist&offset=0&limit=10", "items": [{"external_urls": {"spotify": "https://open.spotify.com/artist/0ZFREHdcfpfQdXwR8mGov4"}, "followers": {"href": null, "total": 58}, "genres": [], "href": "https://api.spotify.com/v1/artists/0ZFREHdcfpfQdXwR8mGov4", "id": "0ZFREHdcfpfQdXwR8mGov4", "images": [{"height": 640, "url": "https://i.scdn.co/image/2ca071cb8a567c1fac9d51944a11a9adbc964c32", "width": 640}, {"height": 300, "url": "https://i.scdn.co/image/8086d5fbe6903006bc8f2e9ca5a3fe7a9bf83de6", "width": 300}, {"height": 64, "url": "https://i.scdn.co/image/e0658ac16cf29b6ebda0b5d0f36bccf53fc3167a", "width": 64}], "name": "Armando Chiliquinga", "popularity": 42, "type": "artist", "uri": "spotify:artist:0ZFREHdcfpfQdXwR8mGov4"}], "limit": 10, "next": null, "offset": 0, "previous": null, "total": 1}}, {"spotify": "https://open.spotify.com/artist/0ZFREHdcfpfQdXwR8mGov4", "followers": 58, "id": "0ZFREHdcfpfQdXwR8mGov4", "images": [{"height": 640, "url": "https://i.scdn.co/image/2ca071cb8a567c1fac9d51944a11a9adbc964c32", "width": 640}, {"height": 300, "url": "https://i.scdn.co/image/8086d5fbe6903006bc8f2e9ca5a3fe7a9bf83de6", "width": 300}, {"height": 64, "url": "https://i.scdn.co/image/e0658ac16cf29b6ebda0b5d0f36bccf53fc3167a", "width": 64}], "name": "Armando Chiliquinga", "popularity": 42, "uri": "spotify:artist:0ZFREHdcfpfQdXwR8mGov4"}, {"artists": {"href": "https://api.spotify.com/v1/search?query=artist%3APRIMER+ENCUENTRO&type=artist&offset=0&limit=10", "items": [], "limit": 10, "next": null, "offset": 0, "previous": null, "total": 0}}, {}]